{
  "id": 675,
  "tier": 1,
  "order": 1,
  "name": "Défense illlusoire",
  "description": "Vous conférez Protection aux alliés à proximité lorsque vous utilisez une compétence de brisure 2.",
  "slot": "Major",
  "facts": [
    {
      "text": "Apply Buff/Condition",
      "type": "Buff",
      "icon": "https://render.guildwars2.com/file/CD77D1FAB7B270223538A8F8ECDA1CFB044D65F4/102834.png",
      "duration": 4,
      "status": "Protection",
      "description": "Dégâts de frappe subis réduits de 33%. La durée est cumulable.",
      "apply_count": 1
    },
    {
      "text": "Apply Buff/Condition",
      "type": "Buff",
      "icon": "https://render.guildwars2.com/file/CD77D1FAB7B270223538A8F8ECDA1CFB044D65F4/102834.png",
      "duration": 2,
      "status": "Protection",
      "description": "Dégâts de frappe subis réduits de 33%. La durée est cumulable.",
      "apply_count": 1
    },
    {
      "text": "Apply Buff/Condition",
      "type": "Buff",
      "icon": "https://render.guildwars2.com/file/CD77D1FAB7B270223538A8F8ECDA1CFB044D65F4/102834.png",
      "duration": 2,
      "status": "Protection",
      "description": "Dégâts de frappe subis réduits de 33%. La durée est cumulable.",
      "apply_count": 1
    },
    {
      "text": "Apply Buff/Condition",
      "type": "Buff",
      "icon": "https://render.guildwars2.com/file/CD77D1FAB7B270223538A8F8ECDA1CFB044D65F4/102834.png",
      "duration": 1,
      "status": "Protection",
      "description": "Dégâts de frappe subis réduits de 33%. La durée est cumulable.",
      "apply_count": 1
    },
    {
      "text": "Rayon",
      "type": "Distance",
      "icon": "https://render.guildwars2.com/file/B0CD8077991E4FB1622D2930337ED7F9B54211D5/156665.png",
      "distance": 360
    },
    {
      "text": "Nombre de cibles",
      "type": "Number",
      "icon": "https://render.guildwars2.com/file/BBE8191A494B0352259C10EADFDACCE177E6DA5B/1770208.png",
      "value": 5
    }
  ],
  "specialization": 45,
  "icon": "https://render.guildwars2.com/file/0E25FD2E32E05D360DB1785818965A4439C1F445/1012463.png"
}